mkdocs_asyncapi_html_plugin/mkdocs_asyncapi_html_plugin.py
mkdocs_asyncapi_html_plugin-0.2.5.dist-info/METADATA
mkdocs_asyncapi_html_plugin-0.2.5.dist-info/WHEEL
mkdocs_asyncapi_html_plugin-0.2.5.dist-info/entry_points.txt
mkdocs_asyncapi_html_plugin-0.2.5.dist-info/top_level.txt
mkdocs_asyncapi_html_plugin-0.2.5.dist-info/RECORD
